deltacode/NOTICE
deltacode/__init__.py
deltacode/cli.py
deltacode/models.py
deltacode/utils.py
deltacode-1.0.0.dist-info/DESCRIPTION.rst
deltacode-1.0.0.dist-info/LICENSE.txt
deltacode-1.0.0.dist-info/METADATA
deltacode-1.0.0.dist-info/RECORD
deltacode-1.0.0.dist-info/WHEEL
deltacode-1.0.0.dist-info/entry_points.txt
deltacode-1.0.0.dist-info/metadata.json
deltacode-1.0.0.dist-info/top_level.txt
