Metadata-Version: 2.0
Name: deltacode
Version: 1.0.0
Summary: Utility for comparing codebases using scancode-toolkit
Home-page: https://github.com/nexb/deltacode
Author: nexB Inc.
Author-email: info@nexb.com
License: Apache-2.0
Platform: UNKNOWN
Classifier: Development Status :: 4 - Beta
Classifier: Intended Audience :: Developers
Classifier: License :: OSI Approved :: Apache Software License
Classifier: Programming Language :: Python
Classifier: Programming Language :: Python :: 2.7
Classifier: Topic :: Utilities
Requires-Dist: click
Requires-Dist: scancode-toolkit
Requires-Dist: unicodecsv
